{
  "main": {
    "id": "3270d10128beebd6",
    "type": "split",
    "children": [
      {
        "id": "a5e7abbc3a57e7c1",
        "type": "tabs",
        "children": [
          {
            "id": "0b0054c8c6b65e33",
            "type": "leaf",
            "pinned": true,
            "state": {
              "type": "markdown",
              "state": {
                "file": "Unity/战斗/帧同步战斗.md",
                "mode": "source",
                "source": false
              },
              "pinned": true
            }
          },
          {
            "id": "bbe965c29dc050fe",
            "type": "leaf",
            "state": {
              "type": "markdown",
              "state": {
                "file": "Unity/打包/HybridCLR&YooAsset/未命名.md",
                "mode": "source",
                "source": false
              }
            }
          },
          {
            "id": "7c349c51c2ff82f8",
            "type": "leaf",
            "state": {
              "type": "markdown",
              "state": {
                "file": "Unity/打包/HybridCLR&YooAsset/未命名.md",
                "mode": "source",
                "source": false
              }
            }
          }
        ],
        "currentTab": 2
      }
    ],
    "direction": "vertical"
  },
  "left": {
    "id": "26d51fdfc100ea97",
    "type": "split",
    "children": [
      {
        "id": "c98910f89b7d8dc9",
        "type": "tabs",
        "dimension": 61.72344689378757,
        "children": [
          {
            "id": "f8a7eda2a99735cf",
            "type": "leaf",
            "state": {
              "type": "file-explorer",
              "state": {
                "sortOrder": "alphabetical"
              }
            }
          },
          {
            "id": "936b4cf76949286f",
            "type": "leaf",
            "state": {
              "type": "search",
              "state": {
                "query": "",
                "matchingCase": false,
                "explainSearch": false,
                "collapseAll": false,
                "extraContext": false,
                "sortOrder": "alphabetical"
              }
            }
          },
          {
            "id": "7751a12b800567b4",
            "type": "leaf",
            "state": {
              "type": "bookmarks",
              "state": {}
            }
          }
        ]
      },
      {
        "id": "c87f52acd7852e9b",
        "type": "tabs",
        "dimension": 38.276553106212425,
        "children": [
          {
            "id": "0617d2d69e526811",
            "type": "leaf",
            "state": {
              "type": "calendar-view",
              "state": {}
            }
          }
        ]
      }
    ],
    "direction": "horizontal",
    "width": 327.5
  },
  "right": {
    "id": "abfee433681e25ee",
    "type": "split",
    "children": [
      {
        "id": "d3caaa2ca124e076",
        "type": "tabs",
        "children": [
          {
            "id": "3a5404156b618047",
            "type": "leaf",
            "state": {
              "type": "backlink",
              "state": {
                "file": "Unity/打包/HybridCLR&YooAsset/未命名.md",
                "collapseAll": true,
                "extraContext": false,
                "sortOrder": "alphabetical",
                "showSearch": false,
                "searchQuery": "",
                "backlinkCollapsed": false,
                "unlinkedCollapsed": true
              }
            }
          },
          {
            "id": "b927bd88216f5865",
            "type": "leaf",
            "state": {
              "type": "outgoing-link",
              "state": {
                "file": "Unity/打包/HybridCLR&YooAsset/未命名.md",
                "linksCollapsed": false,
                "unlinkedCollapsed": false
              }
            }
          },
          {
            "id": "5312d8795cb1daad",
            "type": "leaf",
            "state": {
              "type": "tag",
              "state": {
                "sortOrder": "frequency",
                "useHierarchy": true
              }
            }
          },
          {
            "id": "6490a2fd7323267e",
            "type": "leaf",
            "state": {
              "type": "outline",
              "state": {
                "file": "Unity/打包/HybridCLR&YooAsset/未命名.md"
              }
            }
          }
        ],
        "currentTab": 3
      }
    ],
    "direction": "horizontal",
    "width": 425.5,
    "collapsed": true
  },
  "left-ribbon": {
    "hiddenItems": {
      "obsidian-excalidraw-plugin:新建绘图文件": false,
      "switcher:打开快速切换": false,
      "graph:查看关系图谱": false,
      "canvas:新建白板": false,
      "daily-notes:打开/创建今天的日记": false,
      "templates:插入模板": false,
      "command-palette:打开命令面板": false,
      "obsidian-importer:Open Importer": false,
      "markdown-table-editor:Open Markdown Table Editor": false,
      "pdf-plus:PDF++: Toggle auto-copy": false,
      "pdf-plus:PDF++: Toggle auto-focus": false,
      "pdf-plus:PDF++: Toggle auto-paste": false
    }
  },
  "active": "7c349c51c2ff82f8",
  "lastOpenFiles": [
    "Unity/战斗/帧同步战斗.md",
    "Unity/打包/HybridCLR&YooAsset/未命名.md",
    "Unity/打包/文件压缩/PNG图片格式.md",
    "Unity/打包/文件压缩",
    "Unity/打包/HybridCLR&YooAsset",
    "Unity/打包/Hy + YooAsset",
    "Excalidraw/Map.md",
    "Custom SRP/Draw Calls.md",
    "Custom SRP/Custom Render Pipeline.md",
    "Custom SRP/Custom SRP.md",
    "Unity/战斗/战斗.drawio.crswap",
    "Untitled Diagram.svg",
    "Untitled.md",
    "Unity/战斗/战斗.drawio",
    "Unity/战斗/attachments/Pasted image 20240813093233.png",
    "Unity/战斗/attachments/战斗.drawio",
    "Unity/战斗/attachments",
    "计算机图形学—从0开始构建一个OpenGL软光栅/计算机图形学—从0开始构建一个OpenGL软光栅.md",
    "Unity/战斗",
    "计算机图形学—从0开始构建一个OpenGL软光栅/高级渲染管线功能.md",
    "计算机图形学—从0开始构建一个OpenGL软光栅/图片与纹理.md",
    "计算机图形学—从0开始构建一个OpenGL软光栅/三角形绘制.md",
    "计算机图形学—从0开始构建一个OpenGL软光栅/直线绘制.md",
    "Unity/插件/Addressable.md",
    "conflict-files-obsidian-git.md",
    "Unity/网络编程/2.6 TCP与UDP的可靠性传输_tcp udp 可靠传输-CSDN博客.md",
    "Unity/网络编程/怎么让不可靠的UDP可靠_udp由不可靠传输变为可靠传输-CSDN博客.md",
    "Unity/面试/2023年Unity面试题大全，共十万字面试题总结【收藏一篇足够面试，持续更新】_unity面试题2023-CSDN博客.md",
    "Unity/UGUI/Unity遮罩之Mask、RectMask2D与Sprite Mask适用场景分析 - iwiniwin - 博客园.md",
    "Slurped Pages/unity游戏框架学习-实现CSharp的网络框架.md",
    "Unity/UGUI",
    "Unity/打包/打Android/Unity与Android交互.md",
    "Unity/打包/打Android/attachments/Pasted image 20240624114516.png",
    "Unity/打包/打Android/attachments/Pasted image 20240624114106.png",
    "Unity/打包/打Android/attachments/Pasted image 20240624114006.png",
    "Unity/打包/打Android/attachments/Pasted image 20240624113529.png",
    "Unity/打包/打Android/attachments/Pasted image 20240624113401.png",
    "Unity/打包/打Android/attachments/Pasted image 20240624112817.png",
    "Unity/打包/打Android/attachments/Pasted image 20240624112553.png",
    "Unity/打包/打Android/attachments/Pasted image 20240624112226.png",
    "Unity/打包/打Android/Andorid项目结构.md",
    "Unity/打包/打Android/attachments",
    "Unity/面试/单例模式和静态类的区别 - windpoplar - 博客园.md",
    "Unity/面试/面向对象的三大特性-CSDN博客.md",
    "Unity/面试/面向对象编程三大特性------封装、继承、多态-CSDN博客.md",
    "Unity/面试/60道计算机网络面试题(附答案，背诵版).md",
    "C++/C++.canvas",
    "计算机图形学—从0开始构建一个OpenGL软光栅/从0开始构建OpenGL软光栅.canvas",
    "未命名.canvas"
  ]
}